domplotlib/styles/__init__.py
domplotlib/styles/_plt.py
domplotlib/styles/default.py
domplotlib/styles/domdf.mplstyle
domplotlib/styles/domdf.py
domplotlib/__init__.py
domplotlib/plots.py
domplotlib/py.typed
domplotlib-0.5.0.dist-info/LICENSE
domplotlib-0.5.0.dist-info/METADATA
domplotlib-0.5.0.dist-info/WHEEL
domplotlib-0.5.0.dist-info/entry_points.txt
domplotlib-0.5.0.dist-info/RECORD
