Metadata-Version: 2.2
Name: domplotlib
Version: 0.5.0
Summary: Dom's extensions to matplotlib
Author-email: Dominic Davis-Foster <dominic@davis-foster.co.uk>
License: MIT
Keywords: matplotlib,plotting,visualisation
Home-page: https://github.com/domdfcoding/domplotlib
Project-URL: Issue Tracker, https://github.com/domdfcoding/domplotlib/issues
Project-URL: Source Code, https://github.com/domdfcoding/domplotlib
Project-URL: Documentation, https://domplotlib.readthedocs.io/en/latest
Platform: Windows
Platform: macOS
Platform: Linux
Classifier: Development Status :: 4 - Beta
Classifier: Framework :: Matplotlib
Classifier: Intended Audience :: Developers
Classifier: License :: OSI Approved :: MIT License
Classifier: Operating System :: OS Independent
Classifier: Programming Language :: Python
Classifier: Programming Language :: Python :: 3 :: Only
Classifier: Programming Language :: Python :: 3.6
Classifier: Programming Language :: Python :: 3.7
Classifier: Programming Language :: Python :: 3.8
Classifier: Programming Language :: Python :: 3.9
Classifier: Programming Language :: Python :: 3.10
Classifier: Programming Language :: Python :: 3.11
Classifier: Programming Language :: Python :: 3.12
Classifier: Programming Language :: Python :: 3.13
Classifier: Programming Language :: Python :: Implementation :: CPython
Classifier: Topic :: Software Development :: Libraries :: Python Modules
Classifier: Typing :: Typed
Requires-Python: >=3.6
Requires-Dist: cawdrey>=0.3.0
Requires-Dist: domdf-python-tools>=1.7.0
Requires-Dist: matplotlib>=3.2.2; platform_machine != "aarch64" or python_version > "3.6"
Requires-Dist: matplotlib==3.2.2; platform_machine == "aarch64" and python_version == "3.6"
Requires-Dist: typing-extensions>=3.7.4.3
